{
	"id": "P4SwC5qC9RnCmtT",
	"json": "{\"id\":\"P4SwC5qC9RnCmtT\",\"url\":\"https://www.indiapost.gov.in/VAS/Pages/RTI/suoMotuDisclosure.aspx\",\"uniqueKey\":\"https://www.indiapost.gov.in/VAS/Pages/RTI/suoMotuDisclosure.aspx\",\"method\":\"GET\",\"noRetry\":false,\"retryCount\":0,\"errorMessages\":[],\"headers\":{},\"userData\":{\"depth\":2}}",
	"method": "GET",
	"orderNo": 1740755127380,
	"retryCount": 0,
	"uniqueKey": "https://www.indiapost.gov.in/VAS/Pages/RTI/suoMotuDisclosure.aspx",
	"url": "https://www.indiapost.gov.in/VAS/Pages/RTI/suoMotuDisclosure.aspx"
}